keras_efficientnet_v2/__init__.py
keras_efficientnet_v2/augment.py
keras_efficientnet_v2/efficientnet_v1.py
keras_efficientnet_v2/efficientnet_v2.py
keras_efficientnet_v2/progressive_train_test.py
keras_efficientnet_v2/version.py
keras_efficientnet_v2-1.2.2.dist-info/LICENSE
keras_efficientnet_v2-1.2.2.dist-info/METADATA
keras_efficientnet_v2-1.2.2.dist-info/WHEEL
keras_efficientnet_v2-1.2.2.dist-info/top_level.txt
keras_efficientnet_v2-1.2.2.dist-info/RECORD
