Metadata-Version: 2.1
Name: keras-efficientnet-v2
Version: 1.2.2
Summary: (Unofficial) Tensorflow keras efficientnet v2 with pre-trained
Home-page: https://github.com/leondgarse/keras_efficientnet_v2
Author: Leondgarse
Author-email: leondgarse@google.com
License: Apache 2.0
Keywords: tensorflow keras efficientnet v2 pretrained models
Platform: UNKNOWN
Classifier: Development Status :: 5 - Production/Stable
Classifier: Intended Audience :: Developers
Classifier: Intended Audience :: Science/Research
Classifier: License :: OSI Approved :: Apache Software License
Classifier: Programming Language :: Python :: 3.6
Classifier: Programming Language :: Python :: 3.7
Classifier: Programming Language :: Python :: 3.8
Classifier: Topic :: Scientific/Engineering
Classifier: Topic :: Scientific/Engineering :: Artificial Intelligence
Classifier: Topic :: Software Development
Classifier: Topic :: Software Development :: Libraries
Classifier: Topic :: Software Development :: Libraries :: Python Modules
Requires-Python: >=3.6
License-File: LICENSE
Requires-Dist: tensorflow
